requests_sigv4/__init__.py
requests_sigv4/sigv4request.py
requests_sigv4/version.py
requests_sigv4-0.1.6.dist-info/LICENSE
requests_sigv4-0.1.6.dist-info/METADATA
requests_sigv4-0.1.6.dist-info/WHEEL
requests_sigv4-0.1.6.dist-info/top_level.txt
requests_sigv4-0.1.6.dist-info/RECORD
